[
    {
        "ID": "1",
        "Client": "Cerberus Corp.",
        "Description": "Prothean artifacts",
        "Value": "$ 10.00",
        "Quantity": "50",
        "Sold By": "Bill",
        "Country": "Canada"
    },
    {
        "ID": "2",
        "Client": "Strickland Propane",
        "Description": "Propane and propane accessories",
        "Value": "$ 2265.00",
        "Quantity": "20",
        "Sold By": "Bill",
        "Country": "Canada"
    },
    {
        "ID": "3",
        "Client": "Dunder Mifflin",
        "Description": "Assorted paper-making supplies",
        "Value": "$ 4700.00",
        "Quantity": "10",
        "Sold By": "Ted",
        "Country": "USA"
    },
    {
        "ID": "4",
        "Client": "Utopia Planitia Shipyards",
        "Description": "Dilithium, duranium, assorted shipbuilding supplies",
        "Value": "$ 21750.00",
        "Quantity": "250",
        "Sold By": "Ted",
        "Country": "USA"
    },
    {
        "ID": "5",
        "Client": "Glengarry Estates",
        "Description": "Desks, phones, coffee, steak knives, and one Cadillac",
        "Value": "$ 5000.00",
        "Quantity": "5",
        "Sold By": "Ted",
        "Country": "USA"
    },
    {
        "ID": "6",
        "Client": "Wayne Enterprises",
        "Description": "Suit armor and run-flat tires",
        "Value": "$ 35000.00",
        "Quantity": "25",
        "Sold By": "Angela",
        "Country": "Germany"
    },
    {
        "ID": "7",
        "Client": "Stark Industries",
        "Description": "Armor and rocket fuel",
        "Value": "$ 25000.00",
        "Quantity": "10",
        "Sold By": "Angela",
        "Country": "Germany"
    },
    {
        "ID": "8",
        "Client": "Nakatomi Trading Corp.",
        "Description": "Fire extinguishers and replacement windows",
        "Value": "$ 15000.00",
        "Quantity": "50",
        "Sold By": "Angela",
        "Country": "Germany"
    },
    {
        "ID": "9",
        "Client": "Spaceley Sprockets",
        "Description": "Anti-gravity propulsion units",
        "Value": "$ 25250.00",
        "Quantity": "50",
        "Sold By": "Jill",
        "Country": "UK"
    },
    {
        "ID": "10",
        "Client": "General Products",
        "Description": "Ion engines",
        "Value": "$ 33200.00",
        "Quantity": "40",
        "Sold By": "Jill",
        "Country": "UK"
    }
]